django_live_log/__init__.py
django_live_log/admin.py
django_live_log/models.py
django_live_log/tests.py
django_live_log/urls.py
django_live_log/views.py
django_live_log/templates/.DS_Store
django_live_log/templates/django_live_log/main.html
django_live_log-1.1.4.dist-info/DESCRIPTION.rst
django_live_log-1.1.4.dist-info/METADATA
django_live_log-1.1.4.dist-info/RECORD
django_live_log-1.1.4.dist-info/WHEEL
django_live_log-1.1.4.dist-info/metadata.json
django_live_log-1.1.4.dist-info/top_level.txt
