Metadata-Version: 2.0
Name: django-live-log
Version: 1.1.4
Summary: Simple package for live streaming of file.
Home-page: https://github.com/abdullatheef/django_live_log
Author: Abdul Latheef
Author-email: latheefvkpadi@gmail.com
License: MIT
Platform: UNKNOWN
Classifier: Environment :: Web Environment
Classifier: Framework :: Django
Classifier: Intended Audience :: Developers
Classifier: License :: OSI Approved :: BSD License
Classifier: Operating System :: OS Independent
Classifier: Programming Language :: Python
Classifier: Programming Language :: Python :: 2.7
Classifier: Topic :: Internet :: WWW/HTTP
Classifier: Topic :: Internet :: WWW/HTTP :: Dynamic Content
